syml/__init__.py
syml/basetypes.py
syml/exceptions.py
syml/nodes.py
syml/parsers.py
syml/utils.py
syml-0.6.2.dist-info/LICENSE
syml-0.6.2.dist-info/METADATA
syml-0.6.2.dist-info/WHEEL
syml-0.6.2.dist-info/RECORD
