Metadata-Version: 2.1
Name: syml
Version: 0.6.2
Summary: SYML (Simple YAML-like Markup Language) is a simple markup language with similar structure to YAML, but without all the gewgaws and folderol.
Home-page: https://github.com/eykd/syml/
License: MIT
Author: David Eyk
Author-email: david@worldsenoughstudios.com
Requires-Python: >=3.12,<4.0
Classifier: Development Status :: 4 - Beta
Classifier: License :: OSI Approved :: MIT License
Classifier: Programming Language :: Python
Classifier: Programming Language :: Python :: 3
Classifier: Programming Language :: Python :: 3.12
Classifier: Topic :: Software Development :: Libraries :: Python Modules
Classifier: Topic :: Text Processing :: Markup
Requires-Dist: parsimonious (>=0.10.0,<0.11.0)
Requires-Dist: regex (>=2024.11.6,<2025.0.0)
Project-URL: Repository, https://github.com/eykd/syml
